{
    "Ecole Normale Sup\u00e9rieure de Cachan": {
        "rank": 334,
        "rank_str": 334
    },
    "Aix-Marseille University": {
        "rank": 355,
        "rank_str": 355
    },
    "University of Texas at Dallas": {
        "rank": 366,
        "rank_str": 366
    },
    "Beihang University": {
        "rank": 401,
        "rank_str": "401-410 "
    },
    "Tampere University of Technology": {
        "rank": 431,
        "rank_str": "431-440 "
    },
    "Moscow Institute of Physics and Technology": {
        "rank": 441,
        "rank_str": "441-450 "
    },
    "Taras Shevchenko National University of Kyiv": {
        "rank": 441,
        "rank_str": "441-450 "
    },
    "St Petersburg State Politecnical University": {
        "rank": 451,
        "rank_str": "451-460 "
    },
    "Bogazici University": {
        "rank": 461,
        "rank_str": "461-470 "
    },
    "University of Costa Rica": {
        "rank": 461,
        "rank_str": "461-470 "
    },
    "University of Tartu": {
        "rank": 461,
        "rank_str": "461-470 "
    },
    "American University": {
        "rank": 471,
        "rank_str": "471-480 "
    },
    "University of Zaragoza": {
        "rank": 481,
        "rank_str": "481-490 "
    },
    "Concordia University": {
        "rank": 481,
        "rank_str": "481-490 "
    },
    "Lincoln University": {
        "rank": 481,
        "rank_str": "481-490 "
    }
}