{
    "University of Ulm": {
        "rank": 201,
        "rank_str": "201-225 "
    },
    "Panjab University": {
        "rank": 226,
        "rank_str": "226-250 "
    },
    "University of Nebraska - Lincoln": {
        "rank": 251,
        "rank_str": "251-275 "
    },
    "University of Cologne": {
        "rank": 251,
        "rank_str": "251-275 "
    },
    "University of Plymouth": {
        "rank": 276,
        "rank_str": "276-300 "
    },
    "University of Alaska - Fairbanks": {
        "rank": 276,
        "rank_str": "276-300 "
    },
    "Wuhan University of Technology": {
        "rank": 301,
        "rank_str": "301-350 "
    },
    "Kansas State University": {
        "rank": 301,
        "rank_str": "301-350 "
    },
    "China Medical University - Taiwan": {
        "rank": 351,
        "rank_str": "351-400 "
    },
    "Old Dominion University": {
        "rank": 351,
        "rank_str": "351-400 "
    },
    "University Rovira I Virgili Tarragona": {
        "rank": 351,
        "rank_str": "351-400 "
    },
    "Liverpool John Moores University": {
        "rank": 351,
        "rank_str": "351-400 "
    },
    "King Saud University": {
        "rank": 351,
        "rank_str": "351-400 "
    },
    "San Diego State University": {
        "rank": 351,
        "rank_str": "351-400 "
    },
    "Hanyang University": {
        "rank": 351,
        "rank_str": "351-400 "
    },
    "University of Navarra": {
        "rank": 351,
        "rank_str": "351-400 "
    },
    "Swinburne University of Technology": {
        "rank": 351,
        "rank_str": "351-400 "
    },
    "Indian Institute of Technology, Delhi": {
        "rank": 351,
        "rank_str": "351-400 "
    },
    "University of Bari": {
        "rank": 351,
        "rank_str": "351-400 "
    },
    "Indian Institute of Technology, Kanpur": {
        "rank": 351,
        "rank_str": "351-400 "
    },
    "University of Florence": {
        "rank": 351,
        "rank_str": "351-400 "
    }
}